ys_lib/__init__.py
ys_lib/auth_client.py
ys_lib/bank.py
ys_lib/base.py
ys_lib/cache.py
ys_lib/clickhouse.py
ys_lib/compressor.py
ys_lib/country.py
ys_lib/currency.py
ys_lib/date.py
ys_lib/decorator.py
ys_lib/edge_driver_updater.py
ys_lib/exchange.py
ys_lib/forex.py
ys_lib/interrupt_protect.py
ys_lib/lock.py
ys_lib/math.py
ys_lib/nav.py
ys_lib/parquets.py
ys_lib/progress_console.py
ys_lib/reader.py
ys_lib/sanic_ws_protocol.py
ys_lib/smb_client.py
ys_lib/symbol.py
ys_lib/symbol_em.py
ys_lib/time.py
ys_lib/xt_ws_client.py
ys_lib-1.2.4.dist-info/LICENSE
ys_lib-1.2.4.dist-info/WHEEL
ys_lib-1.2.4.dist-info/METADATA
ys_lib-1.2.4.dist-info/RECORD
