Metadata-Version: 2.1
Name: ys_lib
Version: 1.2.4
Summary: Python SDK for YS
Author-email: ys <popsars@gmail.com>
Requires-Dist: loguru
Requires-Dist: pysmb
Requires-Dist: websockets
Requires-Dist: brotli
Requires-Dist: humanize
Requires-Dist: lz4
Requires-Dist: pypinyin
Requires-Dist: rich
Requires-Dist: zstandard
Requires-Dist: clickhouse_driver
Requires-Dist: clickhouse-cityhash
Requires-Dist: polars
Requires-Dist: requests
Requires-Dist: fs
Requires-Dist: fs.smbfs
Requires-Dist: lxml
Requires-Dist: pywin32; platform_system == 'Windows'
